techind/__init__.py
techind/doubleExponentialMovingAverage.py
techind/exponentialMovingAverage.py
techind/kaufmanAdaptiveMovingAverage.py
techind/mesaAdaptiveMovingAverage.py
techind/simpleMovingAverage.py
techind/triangularMovingAverage.py
techind/trippleExponentialMovingAverage.py
techind/weightedMovingAverage.py
techind-0.0.8.dist-info/LICENSE
techind-0.0.8.dist-info/METADATA
techind-0.0.8.dist-info/WHEEL
techind-0.0.8.dist-info/top_level.txt
techind-0.0.8.dist-info/RECORD
