Metadata-Version: 2.1
Name: techind
Version: 0.0.8
Summary: Collection of technical indicators for financial time series analysis.
Home-page: https://github.com/codersnotepad/techind
Author: Timote WB
Author-email: timote.wb@gmail.com
License: UNKNOWN
Platform: UNKNOWN
Classifier: Programming Language :: Python :: 3.7
Classifier: License :: OSI Approved :: GNU General Public License v3 (GPLv3)
Requires-Dist: numpy (>=1.18.1)
